fastwand/__init__.py
fastwand/cli.py
fastwand-0.1.31.dist-info/METADATA
fastwand-0.1.31.dist-info/WHEEL
fastwand-0.1.31.dist-info/entry_points.txt
fastwand-0.1.31.dist-info/RECORD
