Metadata-Version: 2.3
Name: fastwand
Version: 0.1.31
Summary: CLI tool to initialize FastHTML + Tailwind + DaisyUI projects
Author-email: firefly <promptsiren@gmail.com>
Requires-Python: >=3.11
Requires-Dist: platformdirs>=4.2.0
Requires-Dist: python-fasthtml>=0.9.0
Requires-Dist: requests>=2.31.0
